universal_build/__init__.py
universal_build/_about.py
universal_build/_cli.py
universal_build/_utilities.py
universal_build/build_utils.py
universal_build/helpers/__init__.py
universal_build/helpers/build_docker.py
universal_build/helpers/build_mkdocs.py
universal_build/helpers/build_python.py
universal_build/helpers/openapi_utils.py
universal_build-0.6.18.dist-info/LICENSE
universal_build-0.6.18.dist-info/METADATA
universal_build-0.6.18.dist-info/WHEEL
universal_build-0.6.18.dist-info/entry_points.txt
universal_build-0.6.18.dist-info/top_level.txt
universal_build-0.6.18.dist-info/RECORD
